nextcloud_pywebdav/__init__.py
nextcloud_pywebdav/core.py
nextcloud_pywebdav-1.0.1.dist-info/METADATA
nextcloud_pywebdav-1.0.1.dist-info/WHEEL
nextcloud_pywebdav-1.0.1.dist-info/top_level.txt
nextcloud_pywebdav-1.0.1.dist-info/RECORD
