Metadata-Version: 2.4
Name: nextcloud-pywebdav
Version: 1.0.1
Summary: A simple Python library for Nextcloud WebDAV operations (List, Upload, Download). Designed to be used within the ESA MAAP Project.
Author-email: Joseph Melizza <joseph.melizza@serco.com>
License: MIT
Project-URL: Homepage, https://gitlab.maap.eo.esa.int/joseph.melizza/nextcloud-pywebdav
Project-URL: Bug Tracker, https://gitlab.maap.eo.esa.int/joseph.melizza/nextcloud-pywebdav/issues
Keywords: nextcloud,webdav,client
Requires-Python: >=3.8
Requires-Dist: requests
Requires-Dist: tqdm
